{"get":"players","parameters":{"id":"220","season":"2022"},"errors":[],"results":1,"paging":{"current":1,"total":1},"response":[{"player":{"id":220,"name":"E. Salcedo","firstname":"Eddie Anthony","lastname":"Salcedo Mora","age":22,"birth":{"date":"2001-10-01","place":"Genova","country":"Italy"},"nationality":"Italy","height":"178 cm","weight":null,"injured":false,"photo":"https:\/\/media.api-sports.io\/football\/players\/220.png"},"statistics":[{"team":{"id":495,"name":"Genoa","logo":"https:\/\/media-3.api-sports.io\/football\/teams\/495.png"},"league":{"id":136,"name":"Serie B","country":"Italy","logo":"https:\/\/media.api-sports.io\/football\/leagues\/136.png","flag":"https:\/\/media.api-sports.io\/flags\/it.svg","season":2022},"games":{"appearences":1,"lineups":0,"minutes":12,"number":null,"position":"Attacker","rating":"6.666666","captain":false},"substitutes":{"in":1,"out":0,"bench":3},"shots":{"total":11,"on":5},"goals":{"total":0,"conceded":0,"assists":1,"saves":null},"passes":{"total":156,"key":5,"accuracy":8},"tackles":{"total":8,"blocks":null,"interceptions":2},"duels":{"total":83,"won":35},"dribbles":{"attempts":22,"success":9,"past":null},"fouls":{"drawn":13,"committed":10},"cards":{"yellow":1,"yellowred":0,"red":0},"penalty":{"won":null,"commited":null,"scored":0,"missed":0,"saved":null}},{"team":{"id":508,"name":"Bari","logo":"https:\/\/media-3.api-sports.io\/football\/teams\/508.png"},"league":{"id":136,"name":"Serie B","country":"Italy","logo":"https:\/\/media.api-sports.io\/football\/leagues\/136.png","flag":"https:\/\/media.api-sports.io\/flags\/it.svg","season":2022},"games":{"appearences":15,"lineups":2,"minutes":408,"number":null,"position":"Attacker","rating":"6.666666","captain":false},"substitutes":{"in":13,"out":2,"bench":15},"shots":{"total":11,"on":5},"goals":{"total":2,"conceded":0,"assists":1,"saves":null},"passes":{"total":156,"key":5,"accuracy":8},"tackles":{"total":8,"blocks":null,"interceptions":2},"duels":{"total":83,"won":35},"dribbles":{"attempts":22,"success":9,"past":null},"fouls":{"drawn":13,"committed":10},"cards":{"yellow":0,"yellowred":0,"red":0},"penalty":{"won":null,"commited":null,"scored":0,"missed":0,"saved":null}},{"team":{"id":505,"name":"Inter","logo":"https:\/\/media.api-sports.io\/football\/teams\/505.png"},"league":{"id":135,"name":"Serie A","country":"Italy","logo":"https:\/\/media.api-sports.io\/football\/leagues\/135.png","flag":"https:\/\/media.api-sports.io\/flags\/it.svg","season":2022},"games":{"appearences":0,"lineups":0,"minutes":0,"number":null,"position":"Attacker","rating":null,"captain":false},"substitutes":{"in":0,"out":0,"bench":1},"shots":{"total":null,"on":null},"goals":{"total":0,"conceded":0,"assists":null,"saves":null},"passes":{"total":null,"key":null,"accuracy":null},"tackles":{"total":null,"blocks":null,"interceptions":null},"duels":{"total":null,"won":null},"dribbles":{"attempts":null,"success":null,"past":null},"fouls":{"drawn":null,"committed":null},"cards":{"yellow":0,"yellowred":0,"red":0},"penalty":{"won":null,"commited":null,"scored":0,"missed":0,"saved":null}},{"team":{"id":508,"name":"Bari","logo":"https:\/\/media-3.api-sports.io\/football\/teams\/508.png"},"league":{"id":137,"name":"Coppa Italia","country":"Italy","logo":"https:\/\/media-3.api-sports.io\/football\/leagues\/137.png","flag":"https:\/\/media-3.api-sports.io\/flags\/it.svg","season":2022},"games":{"appearences":1,"lineups":1,"minutes":66,"number":null,"position":"Attacker","rating":null,"captain":false},"substitutes":{"in":0,"out":1,"bench":0},"shots":{"total":null,"on":null},"goals":{"total":0,"conceded":null,"assists":null,"saves":null},"passes":{"total":null,"key":null,"accuracy":null},"tackles":{"total":null,"blocks":null,"interceptions":null},"duels":{"total":null,"won":null},"dribbles":{"attempts":null,"success":null,"past":null},"fouls":{"drawn":null,"committed":null},"cards":{"yellow":0,"yellowred":0,"red":0},"penalty":{"won":null,"commited":null,"scored":null,"missed":null,"saved":null}},{"team":{"id":505,"name":"Inter","logo":"https:\/\/media-3.api-sports.io\/football\/teams\/505.png"},"league":{"id":137,"name":"Coppa Italia","country":"Italy","logo":"https:\/\/media.api-sports.io\/football\/leagues\/137.png","flag":"https:\/\/media-3.api-sports.io\/flags\/it.svg","season":2022},"games":{"appearences":0,"lineups":0,"minutes":0,"number":null,"position":"Attacker","rating":null,"captain":false},"substitutes":{"in":0,"out":0,"bench":0},"shots":{"total":null,"on":null},"goals":{"total":0,"conceded":null,"assists":null,"saves":null},"passes":{"total":null,"key":null,"accuracy":null},"tackles":{"total":null,"blocks":null,"interceptions":null},"duels":{"total":null,"won":null},"dribbles":{"attempts":null,"success":null,"past":null},"fouls":{"drawn":null,"committed":null},"cards":{"yellow":0,"yellowred":0,"red":0},"penalty":{"won":null,"commited":null,"scored":null,"missed":null,"saved":null}},{"team":{"id":505,"name":"Inter","logo":"https:\/\/media.api-sports.io\/football\/teams\/505.png"},"league":{"id":2,"name":"UEFA Champions League","country":"World","logo":"https:\/\/media-3.api-sports.io\/football\/leagues\/2.png","flag":null,"season":2022},"games":{"appearences":0,"lineups":0,"minutes":0,"number":null,"position":"Attacker","rating":null,"captain":false},"substitutes":{"in":0,"out":0,"bench":0},"shots":{"total":null,"on":null},"goals":{"total":0,"conceded":null,"assists":null,"saves":null},"passes":{"total":null,"key":null,"accuracy":null},"tackles":{"total":null,"blocks":null,"interceptions":null},"duels":{"total":null,"won":null},"dribbles":{"attempts":null,"success":null,"past":null},"fouls":{"drawn":null,"committed":null},"cards":{"yellow":0,"yellowred":0,"red":0},"penalty":{"won":null,"commited":null,"scored":null,"missed":null,"saved":null}},{"team":{"id":508,"name":"Bari","logo":"https:\/\/media-3.api-sports.io\/football\/teams\/508.png"},"league":{"id":null,"name":"Club Friendlies","country":null,"logo":null,"flag":null,"season":"2022"},"games":{"appearences":0,"lineups":0,"minutes":0,"number":null,"position":"Attacker","rating":null,"captain":false},"substitutes":{"in":0,"out":0,"bench":0},"shots":{"total":null,"on":null},"goals":{"total":0,"conceded":null,"assists":null,"saves":null},"passes":{"total":null,"key":null,"accuracy":null},"tackles":{"total":null,"blocks":null,"interceptions":null},"duels":{"total":null,"won":null},"dribbles":{"attempts":null,"success":null,"past":null},"fouls":{"drawn":null,"committed":null},"cards":{"yellow":0,"yellowred":0,"red":0},"penalty":{"won":null,"commited":null,"scored":null,"missed":null,"saved":null}},{"team":{"id":505,"name":"Inter","logo":"https:\/\/media-3.api-sports.io\/football\/teams\/505.png"},"league":{"id":null,"name":"Club Friendlies","country":null,"logo":null,"flag":null,"season":"2022"},"games":{"appearences":1,"lineups":0,"minutes":14,"number":null,"position":"Attacker","rating":null,"captain":false},"substitutes":{"in":1,"out":0,"bench":1},"shots":{"total":null,"on":null},"goals":{"total":0,"conceded":null,"assists":null,"saves":null},"passes":{"total":null,"key":null,"accuracy":null},"tackles":{"total":null,"blocks":null,"interceptions":null},"duels":{"total":null,"won":null},"dribbles":{"attempts":null,"success":null,"past":null},"fouls":{"drawn":null,"committed":null},"cards":{"yellow":0,"yellowred":0,"red":0},"penalty":{"won":null,"commited":null,"scored":null,"missed":null,"saved":null}}]}]}